cernopendata_theme/__init__.py
cernopendata_theme/bundles.py
cernopendata_theme/config.py
cernopendata_theme/version.py
cernopendata_theme/views.py
cernopendata_theme/static/apple-touch-icon-114x114.png
cernopendata_theme/static/apple-touch-icon-144x144.png
cernopendata_theme/static/apple-touch-icon-57x57.png
cernopendata_theme/static/apple-touch-icon-72x72.png
cernopendata_theme/static/apple-touch-icon.png
cernopendata_theme/static/favicon.ico
cernopendata_theme/static/img/ALICE.gif
cernopendata_theme/static/img/ATLAS.gif
cernopendata_theme/static/img/CMS.gif
cernopendata_theme/static/img/LHCb.gif
cernopendata_theme/static/img/background.svg
cernopendata_theme/static/img/cern-logo-large.png
cernopendata_theme/static/img/cernopendata-large.png
cernopendata_theme/static/img/cernopendata.svg
cernopendata_theme/static/img/invenio.png
cernopendata_theme/static/scss/frontpage.scss
cernopendata_theme/static/scss/styles.scss
cernopendata_theme/static/scss/variables.scss
cernopendata_theme/templates/cernopendata_theme/footer.html
cernopendata_theme/templates/cernopendata_theme/header.html
cernopendata_theme/templates/cernopendata_theme/page.html
cernopendata_theme-1.0.1.dist-info/top_level.txt
cernopendata_theme-1.0.1.dist-info/entry_points.txt
cernopendata_theme-1.0.1.dist-info/METADATA
cernopendata_theme-1.0.1.dist-info/DESCRIPTION.rst
cernopendata_theme-1.0.1.dist-info/metadata.json
cernopendata_theme-1.0.1.dist-info/WHEEL
cernopendata_theme-1.0.1.dist-info/RECORD
