Metadata-Version: 2.0
Name: cernopendata-theme
Version: 1.0.1
Summary: Theme for CERN Open Data Portal.
Home-page: https://github.com/cernopendata/cernopendata-theme
Author: CERN
Author-email: info@inveniosoftware.org
License: GPLv2
Keywords: CERN Open Data Theme
Platform: any
Classifier: Environment :: Web Environment
Classifier: Intended Audience :: Developers
Classifier: License :: OSI Approved :: GNU General Public License v2 (GPLv2)
Classifier: Operating System :: OS Independent
Classifier: Programming Language :: Python
Classifier: Topic :: Internet :: WWW/HTTP :: Dynamic Content
Classifier: Topic :: Software Development :: Libraries :: Python Modules
Classifier: Programming Language :: Python :: 2
Classifier: Programming Language :: Python :: 2.7
Classifier: Programming Language :: Python :: 3
Classifier: Programming Language :: Python :: 3.5
Classifier: Development Status :: 5 - Production/Stable
Requires-Dist: Flask (>=0.11.1)
Requires-Dist: invenio-assets (>=1.0.0b4)
Requires-Dist: invenio-i18n (>=1.0.0b1)
Requires-Dist: invenio-theme (>=1.0.0a16)
Provides-Extra: all
Requires-Dist: Sphinx (>=1.5.1); extra == 'all'
Requires-Dist: check-manifest (>=0.25); extra == 'all'
Requires-Dist: coverage (>=4.0); extra == 'all'
Requires-Dist: isort (>=4.2.2); extra == 'all'
Requires-Dist: pydocstyle (>=1.0.0); extra == 'all'
Requires-Dist: pytest-cache (>=1.0); extra == 'all'
Requires-Dist: pytest-cov (>=1.8.0); extra == 'all'
Requires-Dist: pytest-pep8 (>=1.0.6); extra == 'all'
Requires-Dist: pytest (>=2.8.0); extra == 'all'
Requires-Dist: Sphinx (>=1.5.1); extra == 'all'
Requires-Dist: check-manifest (>=0.25); extra == 'all'
Requires-Dist: coverage (>=4.0); extra == 'all'
Requires-Dist: isort (>=4.2.2); extra == 'all'
Requires-Dist: pydocstyle (>=1.0.0); extra == 'all'
Requires-Dist: pytest-cache (>=1.0); extra == 'all'
Requires-Dist: pytest-cov (>=1.8.0); extra == 'all'
Requires-Dist: pytest-pep8 (>=1.0.6); extra == 'all'
Requires-Dist: pytest (>=2.8.0); extra == 'all'
Provides-Extra: docs
Requires-Dist: Sphinx (>=1.5.1); extra == 'docs'
Provides-Extra: tests
Requires-Dist: check-manifest (>=0.25); extra == 'tests'
Requires-Dist: coverage (>=4.0); extra == 'tests'
Requires-Dist: isort (>=4.2.2); extra == 'tests'
Requires-Dist: pydocstyle (>=1.0.0); extra == 'tests'
Requires-Dist: pytest-cache (>=1.0); extra == 'tests'
Requires-Dist: pytest-cov (>=1.8.0); extra == 'tests'
Requires-Dist: pytest-pep8 (>=1.0.6); extra == 'tests'
Requires-Dist: pytest (>=2.8.0); extra == 'tests'
